watchmen_auth/__init__.py
watchmen_auth/auth_helper.py
watchmen_auth/authentication.py
watchmen_auth/authorization.py
watchmen_auth/fake_principal_service.py
watchmen_auth/principal_service.py
watchmen_auth/settings.py
watchmen_auth-18.0.1.dist-info/METADATA
watchmen_auth-18.0.1.dist-info/WHEEL
watchmen_auth-18.0.1.dist-info/licenses/LICENSE
watchmen_auth-18.0.1.dist-info/RECORD
